PyLMNN-1.5.1.dist-info/DESCRIPTION.rst
PyLMNN-1.5.1.dist-info/METADATA
PyLMNN-1.5.1.dist-info/RECORD
PyLMNN-1.5.1.dist-info/WHEEL
PyLMNN-1.5.1.dist-info/metadata.json
PyLMNN-1.5.1.dist-info/top_level.txt
examples/__init__.py
examples/data_fetch.py
examples/demo.py
examples/minimal.py
examples/unlzw.py
pylmnn/__init__.py
pylmnn/bayesopt.py
pylmnn/helpers.py
pylmnn/lmnn.py
pylmnn/plots.py
