Metadata-Version: 2.0
Name: PyLMNN
Version: 1.5.1
Summary: Large Margin Nearest Neighbor implementation in python
Home-page: https://github.com/johny-c/pylmnn.git
Author: John Chiotellis
Author-email: johnyc.code@gmail.com
License: new BSD
Platform: UNKNOWN
Classifier: Development Status :: 4 - Beta
Classifier: License :: OSI Approved :: GNU General Public License v3 (GPLv3)
Classifier: Natural Language :: English
Classifier: Operating System :: MacOS :: MacOS X
Classifier: Operating System :: Microsoft :: Windows
Classifier: Operating System :: POSIX :: Linux
Classifier: Programming Language :: Python :: 3
Classifier: Programming Language :: Python :: 3.5
Classifier: Programming Language :: Python :: 3.6
Classifier: Topic :: Scientific/Engineering :: Artificial Intelligence
Requires-Dist: GPyOpt (>=1.0.3)
Requires-Dist: matplotlib (>=1.5.3)
Requires-Dist: numpy (>=1.11)
Requires-Dist: scikit-learn (>=0.18)
Requires-Dist: scipy (>=0.18)
